PyTango/__init__.py
pytango.libs/libCOS4-8d744e42.so.3.3
pytango.libs/libabsl_base-9e4554b4.so.2505.0.0
pytango.libs/libabsl_city-3c6c2811.so.2505.0.0
pytango.libs/libabsl_civil_time-35e195b9.so.2505.0.0
pytango.libs/libabsl_cord-d014d6a7.so.2505.0.0
pytango.libs/libabsl_cord_internal-5a925a4b.so.2505.0.0
pytango.libs/libabsl_cordz_functions-3823437c.so.2505.0.0
pytango.libs/libabsl_cordz_handle-5fbbf4bb.so.2505.0.0
pytango.libs/libabsl_cordz_info-25daa96b.so.2505.0.0
pytango.libs/libabsl_crc32c-4e1f1f91.so.2505.0.0
pytango.libs/libabsl_crc_cord_state-42d5420e.so.2505.0.0
pytango.libs/libabsl_crc_cpu_detect-752ff2f7.so.2505.0.0
pytango.libs/libabsl_crc_internal-a0a8bcdc.so.2505.0.0
pytango.libs/libabsl_debugging_internal-0d160140.so.2505.0.0
pytango.libs/libabsl_decode_rust_punycode-7d6cb1e8.so.2505.0.0
pytango.libs/libabsl_demangle_internal-1eeb532c.so.2505.0.0
pytango.libs/libabsl_demangle_rust-1f587b8f.so.2505.0.0
pytango.libs/libabsl_die_if_null-f3395278.so.2505.0.0
pytango.libs/libabsl_examine_stack-4717500c.so.2505.0.0
pytango.libs/libabsl_exponential_biased-dc85a295.so.2505.0.0
pytango.libs/libabsl_flags_commandlineflag-8423e7aa.so.2505.0.0
pytango.libs/libabsl_flags_commandlineflag_internal-d48749ba.so.2505.0.0
pytango.libs/libabsl_flags_config-46f6193d.so.2505.0.0
pytango.libs/libabsl_flags_internal-14460a9b.so.2505.0.0
pytango.libs/libabsl_flags_marshalling-c210e7e6.so.2505.0.0
pytango.libs/libabsl_flags_private_handle_accessor-e863920e.so.2505.0.0
pytango.libs/libabsl_flags_program_name-c534bc45.so.2505.0.0
pytango.libs/libabsl_flags_reflection-51076499.so.2505.0.0
pytango.libs/libabsl_graphcycles_internal-4537014e.so.2505.0.0
pytango.libs/libabsl_hash-1596a723.so.2505.0.0
pytango.libs/libabsl_hashtablez_sampler-b4dbac5a.so.2505.0.0
pytango.libs/libabsl_int128-a222e9ce.so.2505.0.0
pytango.libs/libabsl_kernel_timeout_internal-896d8957.so.2505.0.0
pytango.libs/libabsl_leak_check-112dbd4b.so.2505.0.0
pytango-10.0.3.dist-info/METADATA
pytango-10.0.3.dist-info/WHEEL
pytango-10.0.3.dist-info/RECORD
pytango-10.0.3.dist-info/licenses/LICENSE.txt
