Metadata-Version: 2.1
Name: pytango
Version: 10.0.3
Summary: Python bindings for the cppTango library; part of the Tango Distributed Control System toolkit
Author: Coutinho
Maintainer: Anton Joubert, Yury Matveyev
Classifier: Development Status :: 5 - Production/Stable
Classifier: Environment :: Other Environment
Classifier: Intended Audience :: Developers
Classifier: License :: OSI Approved :: GNU Library or Lesser General Public License (LGPL)
Classifier: Natural Language :: English
Classifier: Operating System :: Microsoft :: Windows
Classifier: Operating System :: MacOS
Classifier: Operating System :: POSIX
Classifier: Operating System :: POSIX :: Linux
Classifier: Operating System :: Unix
Classifier: Programming Language :: C
Classifier: Programming Language :: Python
Classifier: Programming Language :: Python :: 3.9
Classifier: Programming Language :: Python :: 3.10
Classifier: Programming Language :: Python :: 3.11
Classifier: Programming Language :: Python :: 3.12
Classifier: Programming Language :: Python :: 3.13
Classifier: Topic :: Scientific/Engineering
Classifier: Topic :: Software Development :: Libraries
Project-URL: homepage, https://www.tango-controls.org/
Project-URL: documentation, https://pytango.readthedocs.io
Project-URL: repository, https://gitlab.com/tango-controls/pytango.git
Project-URL: changelog, https://gitlab.com/tango-controls/pytango/-/releases
Requires-Python: >=3.9
Requires-Dist: numpy<3,>=1.19.3
Requires-Dist: packaging
Requires-Dist: psutil>=5.3.0
Requires-Dist: typing_extensions>=4.5.0; python_version < "3.13"
Provides-Extra: telemetry
Requires-Dist: opentelemetry-api; extra == "telemetry"
Requires-Dist: opentelemetry-sdk; extra == "telemetry"
Requires-Dist: opentelemetry-exporter-otlp-proto-grpc; extra == "telemetry"
Requires-Dist: opentelemetry-exporter-otlp-proto-http; extra == "telemetry"
Provides-Extra: tests
Requires-Dist: gevent>=20.0; extra == "tests"
Requires-Dist: pytest; extra == "tests"
Requires-Dist: pytest-asyncio>=0.24; extra == "tests"
Requires-Dist: pytest-cov; extra == "tests"
Requires-Dist: pytest-forked; extra == "tests"
Requires-Dist: pytest-timeout; extra == "tests"
